{
  "version":  "1.0",
  "mappings": {
    /*
    Unicode blocks covered:
    - 0: Basic Latin (on normal keyboard)
    - 1: 
    - 2: Latin Extended-A, except
        * Ľ ľ : [',.]l are all taken
        * ŉ : is deprecated (good, 'cause [,']n are taken)
     
    */

    // Punctuation
    "!!": "¡",
    "??": "¿",
    "  ": " ", // NBSP
    "--": "–", // en-dash
    "---": "—", // em-dash

    // Ligatures or other letters
    "ae": "æ",
    "AE": "Æ",

    "ij": "ĳ",
    "IJ": "Ĳ",

    "ss": "ß",

    "oe": "œ",
    "OE": "Œ",

    "th": "þ",
    "TH": "Þ",

    "dh": "ð",
    "DH": "Ð", // also under '-D'

    "kk": "ĸ", //?

    "ng": "ŋ",
    "NG": "Ŋ",

    "sf": "ſ",

    "AA": "∀",
    "EE": "∃",

    // Diacritics
    "-a": "ā",
    "-d": "đ",
    "-e": "ē",
    "-h": "ħ",
    "-i": "ī",
    "-l": "ł",
    "-o": "ō",
    "-t": "ŧ",
    "-u": "ū",

    "-A": "Ā",
    "-D": "Đ",
    "-E": "Ē",
    "-H": "Ħ",
    "-I": "Ī",
    "-L": "Ł",
    "-O": "Ō",
    "-T": "Ŧ",
    "-U": "Ū",

    "ua": "ă",
    "ue": "ĕ",
    "ug": "ğ",
    "ui": "ĭ",
    "uo": "ŏ",
    "uu": "ŭ",

    "uA": "Ă",
    "uE": "Ĕ",
    "uG": "Ğ",
    "uI": "Ĭ",
    "uO": "Ŏ",
    "uU": "ŭ",

    ",a": "ą",
    ",c": "ç",
    ",e": "ę",
    ",g": "ģ",
    ",i": "į",
    ",k": "ķ",
    ",l": "ļ",
    ",n": "ņ",
    ",r": "ŗ",
    ",s": "ş",
    ",t": "ţ",
    ",u": "ų",

    ",A": "Ą",
    ",C": "Ç",
    ",E": "Ę",
    ",G": "Ģ",
    ",I": "Į",
    ",K": "Ķ",
    ",L": "Ļ",
    ",N": "Ņ",
    ",R": "Ŗ",
    ",S": "Ş",
    ",T": "Ţ",
    ",U": "Ų",

    ".c": "ċ",
    ".e": "ė",
    ".g": "ġ",
    ".i": "ı",
    ".l": "ŀ",
    ".z": "ż",

    ".C": "Ċ",
    ".E": "Ė",
    ".G": "Ġ",
    ".I": "İ",
    ".L": "Ŀ",
    ".Z": "Ż",

    "vc": "č",
    //vd: see 'd
    "ve": "ě",
    "vn": "ň",
    "vr": "ř",
    "vs": "š",
    //vt: see 't
    "vz": "ž",

    "vC": "Č",
    "vD": "Ď",
    "vE": "Ě",
    "vN": "Ň",
    "vR": "Ř",
    "vS": "Š",
    "vT": "Ť",
    "vZ": "Ž",

    "`a": "à",
    "`e": "è",
    "`i": "ì",
    "`o": "ò",
    "`u": "ù",

    "`A": "À",
    "`E": "È",
    "`I": "Ì",
    "`O": "Ò",
    "`U": "Ù",

    "'a": "á",
    "'c": "ć",
    "'d": "ď",
    "'e": "é",
    "'i": "í",
    "'l": "ĺ",
    "'n": "ń",
    "'o": "ó",
    "'r": "ŕ",
    "'s": "ś",
    "'t": "ť",
    "'u": "ú",
    "'y": "ý",
    "'z": "ź",

    "'A": "Á",
    "'C": "Ć",
    "'E": "É",
    "'I": "Í",
    "'L": "Ĺ",
    "'N": "Ń",
    "'O": "Ó",
    "'R": "Ŕ",
    "'S": "Ś",
    "'U": "Ú",
    "'Y": "Ý",
    "'Z": "Ź",

    "''o": "ő",
    "''u": "ű",

    "''O": "Ő",
    "''U": "Ű",

    "^a": "â",
    "^e": "ê",
    "^c": "ĉ",
    "^h": "ĥ",
    "^i": "î",
    "^j": "ĵ",
    "^g": "ĝ",
    "^o": "ô",
    "^s": "ŝ",
    "^u": "û",
    "^w": "ŵ",
    "^y": "ŷ",

    "^A": "Â",
    "^E": "Ê",
    "^C": "Ĉ",
    "^H": "Ĥ",
    "^I": "Î",
    "^J": "Ĵ",
    "^G": "Ĝ",
    "^O": "Ô",
    "^S": "Ŝ",
    "^U": "Û",
    "^W": "Ŵ",
    "^Y": "Ŷ",

    "~a": "ã",
    "~i": "ĩ",
    "~n": "ñ",
    "~o": "õ",
    "~u": "ũ",

    "~A": "Ã",
    "~I": "Ĩ",
    "~N": "Ñ",
    "~O": "Õ",
    "~U": "Ũ",

    "\"a": "ä",
    "\"e": "ë",
    "\"i": "ï",
    "\"o": "ö",
    "\"u": "ü",
    "\"y": "ÿ",

    "\"A": "Ä",
    "\"E": "Ë",
    "\"I": "Ï",
    "\"O": "Ö",
    "\"U": "Ü",
    "\"Y": "Ÿ",

    "/o": "ø",
    "/O": "Ø",

    "ou": "ů",
    "oa": "å",

    "oU": "Ů",
    "oA": "Å",

    // Quotes
    "\"<": "“",
    "\">": "”",
    "'<": "‘",
    "'>": "’",
    "<<": "«",
    ">>": "»",

    // Superscripts
    "^0": "⁰",
    "^1": "¹",
    "^2": "²",
    "^3": "³",
    "^4": "⁴",
    "^5": "⁵",
    "^6": "⁶",
    "^7": "⁷",
    "^8": "⁸",
    "^9": "⁹",
    "^+": "⁺",
    "^-": "⁻",
    "^=": "⁼",
    "^n": "ⁿ",
    "^(": "⁽",
    "^)": "⁾",

    // Fractions
    "1/4": "¼",
    "1/2": "½",
    "3/4": "¾",
    "1/7": "⅐",
    "1/9": "⅑",
    "1/10": "⅒",
    "1/3": "⅓",
    "2/3": "⅔",
    "1/5": "⅕",
    "2/5": "⅖",
    "3/5": "⅗",
    "4/5": "⅘",
    "1/6": "⅙",
    "5/6": "⅚",
    "1/8": "⅛",
    "3/8": "⅜",
    "5/8": "⅝",
    "7/8": "⅞",
    "0/3": "↉",

    // Mathematical symbols
    ":-": "÷",
    "+-": "±",
    "-+": "∓",
    "/=": "",
    "=<": "≤", // due to double-arrow...
    ">=": "≥",
    "/<": "≮",
    "/>": "≯",
    "~~": "≈",
    "/~~": "≉",
    "~-": "≃",
    "/~-": "≄",
    "-~": "≂",
    "~~~": "≋",
    "~~-": "≊",
    "~=": "≅",
    "~/=": "≆",
    "/~=": "≇",
    "::": "∷",
    "/\\": "∧",
    "\\/": "∨",

    // Greek
    "ga": "α", // Alpha
    "gb": "β", // Beta
    "gc": "χ", // Chi
    "gd": "δ", // Delta
    "gg": "γ", // Gamma
    "ge": "ε", // Epsilon
    "gth": "θ", // THeta
    "gi": "ι", // Iota
    "gk": "κ", // Kappa
    "gl": "λ", // Lambda
    "gm": "μ", // Mu
    "gn": "ν", // Nu
    "goi": "ο", // OmIcron
    "goe": "ω", // OmEga
    "gp": "π", // Pi
    "gps": "ψ", // PSi
    "gph": "φ", // PHi
    "gr": "ρ", // Rho
    "gs": "σ", // Sigma
    "gsf": "ς", // Sigma Final
    "gt": "τ", // Tau
    "gu": "υ", // Upsilon
    "gx": "ξ", // Xi
    "gy": "η", // eta (capital is Y)
    "gz": "ζ", // Zeta

    "gA": "Α",
    "gB": "Β",
    "gC": "Χ",
    "gG": "Γ",
    "gD": "Δ",
    "gE": "Ε",
    "gTH": "Θ",
    "gI": "Ι",
    "gK": "Κ",
    "gL": "Λ",
    "gM": "Μ",
    "gN": "Ν",
    "gOI": "Ο",
    "gOE": "Ω",
    "gP": "Π",
    "gPS": "Ψ",
    "gPH": "Φ",
    "gR": "Ρ",
    "gS": "Σ",
    "gT": "Τ",
    "gU": "Υ",
    "gX": "Ξ",
    "gY": "Η",
    "gZ": "Ζ",

    // Arrows
    "->": "→",
    "~>": "↝",
    "-->": "⟶",
    "<-": "←",
    "<~": "↜",
    "<--": "⟵",
    "<->": "↔",
    "<-->": "⟷",
    "<<-": "↞",
    "->>": "↠",
    "<-<": "↢",
    ">->": "↣",
    "<-|": "↤",
    "<--|": "⟻",
    "|->": "↦",
    "|-->": "⟼",
    "<-)": "↩",
    "<-(": "↫",
    "(->": "↪",
    ")->": "↬",
    "/<-": "↚",
    "/->": "↛",

    "<=": "⇐",
    "<==": "⟸",
    "=>": "⇒",
    "==>": "⟹",
    "<=>": "⇔",
    "<==>": "⟺",
    "<==|": "⟽",
    "|==>": "⟾",

    // Signs
    "TM": "™",
    "SM": "℠",
    "OR": "®",
    "OC": "©",
    "OP": "℗",
    "Rx": "℞",
    "c/o": "℅",

    // Currencies
    "=C": "€",
    "=W": "₩"

  }
}